CHANGES.md
LICENSE
MANIFEST.in
README.md
setup.py
grnhse/__init__.py
grnhse/exceptions.py
grnhse/util.py
grnhse/harvest/__init__.py
grnhse/harvest/api.py
grnhse/harvest/versions.py
grnhse_api.egg-info/PKG-INFO
grnhse_api.egg-info/SOURCES.txt
grnhse_api.egg-info/dependency_links.txt
grnhse_api.egg-info/requires.txt
grnhse_api.egg-info/top_level.txt